{
  "fields": [
    {
      "aggregatable": true,
      "custom": false,
      "defaultValue": null,
      "extraTypeInfo": null,
      "filterable": true,
      "groupable": true,
      "inlineHelpText": null,
      "label": "ContentDocument ID",
      "name": "Id",
      "nillable": false,
      "picklistValues": [],
      "referenceTo": [],
      "relationshipName": null,
      "sortable": true,
      "type": "id"
    },
    {
      "aggregatable": true,
      "custom": false,
      "defaultValue": null,
      "extraTypeInfo": null,
      "filterable": true,
      "groupable": true,
      "inlineHelpText": null,
      "label": "Criado pelo ID",
      "name": "CreatedById",
      "nillable": false,
      "picklistValues": [],
      "referenceTo": [
        "User"
      ],
      "relationshipName": "CreatedBy",
      "sortable": true,
      "type": "reference"
    },
    {
      "aggregatable": true,
      "custom": false,
      "defaultValue": null,
      "extraTypeInfo": null,
      "filterable": true,
      "groupable": false,
      "inlineHelpText": null,
      "label": "Criado em",
      "name": "CreatedDate",
      "nillable": false,
      "picklistValues": [],
      "referenceTo": [],
      "relationshipName": null,
      "sortable": true,
      "type": "datetime"
    },
    {
      "aggregatable": true,
      "custom": false,
      "defaultValue": null,
      "extraTypeInfo": null,
      "filterable": true,
      "groupable": true,
      "inlineHelpText": null,
      "label": "Última modificação pelo ID",
      "name": "LastModifiedById",
      "nillable": false,
      "picklistValues": [],
      "referenceTo": [
        "User"
      ],
      "relationshipName": "LastModifiedBy",
      "sortable": true,
      "type": "reference"
    },
    {
      "aggregatable": true,
      "custom": false,
      "defaultValue": null,
      "extraTypeInfo": null,
      "filterable": true,
      "groupable": false,
      "inlineHelpText": null,
      "label": "Data da última modificação",
      "name": "LastModifiedDate",
      "nillable": false,
      "picklistValues": [],
      "referenceTo": [],
      "relationshipName": null,
      "sortable": true,
      "type": "datetime"
    },
    {
      "aggregatable": false,
      "custom": false,
      "defaultValue": false,
      "extraTypeInfo": null,
      "filterable": true,
      "groupable": true,
      "inlineHelpText": null,
      "label": "Está arquivado",
      "name": "IsArchived",
      "nillable": false,
      "picklistValues": [],
      "referenceTo": [],
      "relationshipName": null,
      "sortable": true,
      "type": "boolean"
    },
    {
      "aggregatable": true,
      "custom": false,
      "defaultValue": null,
      "extraTypeInfo": null,
      "filterable": true,
      "groupable": true,
      "inlineHelpText": null,
      "label": "ID do usuário",
      "name": "ArchivedById",
      "nillable": true,
      "picklistValues": [],
      "referenceTo": [
        "User"
      ],
      "relationshipName": null,
      "sortable": true,
      "type": "reference"
    },
    {
      "aggregatable": true,
      "custom": false,
      "defaultValue": null,
      "extraTypeInfo": null,
      "filterable": true,
      "groupable": true,
      "inlineHelpText": null,
      "label": "Data do arquivamento",
      "name": "ArchivedDate",
      "nillable": true,
      "picklistValues": [],
      "referenceTo": [],
      "relationshipName": null,
      "sortable": true,
      "type": "date"
    },
    {
      "aggregatable": false,
      "custom": false,
      "defaultValue": false,
      "extraTypeInfo": null,
      "filterable": true,
      "groupable": true,
      "inlineHelpText": null,
      "label": "É excluído",
      "name": "IsDeleted",
      "nillable": false,
      "picklistValues": [],
      "referenceTo": [],
      "relationshipName": null,
      "sortable": true,
      "type": "boolean"
    },
    {
      "aggregatable": true,
      "custom": false,
      "defaultValue": null,
      "extraTypeInfo": null,
      "filterable": true,
      "groupable": true,
      "inlineHelpText": null,
      "label": "ID do proprietário",
      "name": "OwnerId",
      "nillable": false,
      "picklistValues": [],
      "referenceTo": [
        "User"
      ],
      "relationshipName": "Owner",
      "sortable": true,
      "type": "reference"
    },
    {
      "aggregatable": true,
      "custom": false,
      "defaultValue": null,
      "extraTypeInfo": null,
      "filterable": true,
      "groupable": false,
      "inlineHelpText": null,
      "label": "Modstamp do sistema",
      "name": "SystemModstamp",
      "nillable": false,
      "picklistValues": [],
      "referenceTo": [],
      "relationshipName": null,
      "sortable": true,
      "type": "datetime"
    },
    {
      "aggregatable": true,
      "custom": false,
      "defaultValue": null,
      "extraTypeInfo": null,
      "filterable": true,
      "groupable": true,
      "inlineHelpText": null,
      "label": "Título",
      "name": "Title",
      "nillable": false,
      "picklistValues": [],
      "referenceTo": [],
      "relationshipName": null,
      "sortable": true,
      "type": "string"
    },
    {
      "aggregatable": true,
      "custom": false,
      "defaultValue": "U",
      "extraTypeInfo": null,
      "filterable": true,
      "groupable": true,
      "inlineHelpText": null,
      "label": "Publicar status",
      "name": "PublishStatus",
      "nillable": false,
      "picklistValues": [
        {
          "active": true,
          "defaultValue": true,
          "label": "Upload interrompido",
          "validFor": null,
          "value": "U"
        },
        {
          "active": true,
          "defaultValue": false,
          "label": "Público",
          "validFor": null,
          "value": "P"
        },
        {
          "active": true,
          "defaultValue": false,
          "label": "Biblioteca particular",
          "validFor": null,
          "value": "R"
        }
      ],
      "referenceTo": [],
      "relationshipName": null,
      "sortable": true,
      "type": "picklist"
    },
    {
      "aggregatable": true,
      "custom": false,
      "defaultValue": null,
      "extraTypeInfo": null,
      "filterable": true,
      "groupable": true,
      "inlineHelpText": null,
      "label": "ID da última versão publicada",
      "name": "LatestPublishedVersionId",
      "nillable": true,
      "picklistValues": [],
      "referenceTo": [
        "ContentVersion"
      ],
      "relationshipName": "LatestPublishedVersion",
      "sortable": true,
      "type": "reference"
    },
    {
      "aggregatable": true,
      "custom": false,
      "defaultValue": null,
      "extraTypeInfo": null,
      "filterable": true,
      "groupable": true,
      "inlineHelpText": null,
      "label": "ID pai",
      "name": "ParentId",
      "nillable": true,
      "picklistValues": [],
      "referenceTo": [
        "ContentWorkspace"
      ],
      "relationshipName": null,
      "sortable": true,
      "type": "reference"
    },
    {
      "aggregatable": true,
      "custom": false,
      "defaultValue": null,
      "extraTypeInfo": null,
      "filterable": true,
      "groupable": false,
      "inlineHelpText": null,
      "label": "Data da última visualização",
      "name": "LastViewedDate",
      "nillable": true,
      "picklistValues": [],
      "referenceTo": [],
      "relationshipName": null,
      "sortable": true,
      "type": "datetime"
    },
    {
      "aggregatable": true,
      "custom": false,
      "defaultValue": null,
      "extraTypeInfo": null,
      "filterable": true,
      "groupable": false,
      "inlineHelpText": null,
      "label": "Última data citada",
      "name": "LastReferencedDate",
      "nillable": true,
      "picklistValues": [],
      "referenceTo": [],
      "relationshipName": null,
      "sortable": true,
      "type": "datetime"
    },
    {
      "aggregatable": true,
      "custom": false,
      "defaultValue": null,
      "extraTypeInfo": "plaintextarea",
      "filterable": true,
      "groupable": false,
      "inlineHelpText": null,
      "label": "Descrição",
      "name": "Description",
      "nillable": true,
      "picklistValues": [],
      "referenceTo": [],
      "relationshipName": null,
      "sortable": true,
      "type": "textarea"
    },
    {
      "aggregatable": true,
      "custom": false,
      "defaultValue": null,
      "extraTypeInfo": null,
      "filterable": true,
      "groupable": true,
      "inlineHelpText": null,
      "label": "Tamanho",
      "name": "ContentSize",
      "nillable": true,
      "picklistValues": [],
      "referenceTo": [],
      "relationshipName": null,
      "sortable": true,
      "type": "int"
    },
    {
      "aggregatable": true,
      "custom": false,
      "defaultValue": null,
      "extraTypeInfo": null,
      "filterable": true,
      "groupable": true,
      "inlineHelpText": null,
      "label": "Tipo de arquivo",
      "name": "FileType",
      "nillable": true,
      "picklistValues": [],
      "referenceTo": [],
      "relationshipName": null,
      "sortable": true,
      "type": "string"
    },
    {
      "aggregatable": true,
      "custom": false,
      "defaultValue": null,
      "extraTypeInfo": null,
      "filterable": true,
      "groupable": true,
      "inlineHelpText": null,
      "label": "Extensão de arquivo",
      "name": "FileExtension",
      "nillable": true,
      "picklistValues": [],
      "referenceTo": [],
      "relationshipName": null,
      "sortable": true,
      "type": "string"
    },
    {
      "aggregatable": true,
      "custom": false,
      "defaultValue": "A",
      "extraTypeInfo": null,
      "filterable": true,
      "groupable": true,
      "inlineHelpText": null,
      "label": "Evitar que outras pessoas compartilhem e cancelem o compartilhamento",
      "name": "SharingOption",
      "nillable": true,
      "picklistValues": [
        {
          "active": true,
          "defaultValue": true,
          "label": "Congelamento de compartilhamento desligado",
          "validFor": null,
          "value": "A"
        },
        {
          "active": true,
          "defaultValue": false,
          "label": "Congelamento de compartilhamento ligado",
          "validFor": null,
          "value": "R"
        }
      ],
      "referenceTo": [],
      "relationshipName": null,
      "sortable": true,
      "type": "picklist"
    },
    {
      "aggregatable": true,
      "custom": false,
      "defaultValue": "N",
      "extraTypeInfo": null,
      "filterable": true,
      "groupable": true,
      "inlineHelpText": null,
      "label": "Privacidade de arquivo em registros",
      "name": "SharingPrivacy",
      "nillable": true,
      "picklistValues": [
        {
          "active": true,
          "defaultValue": true,
          "label": "Visível a qualquer um com acesso ao registro",
          "validFor": null,
          "value": "N"
        },
        {
          "active": true,
          "defaultValue": false,
          "label": "Privado em registros",
          "validFor": null,
          "value": "P"
        }
      ],
      "referenceTo": [],
      "relationshipName": null,
      "sortable": true,
      "type": "picklist"
    },
    {
      "aggregatable": true,
      "custom": false,
      "defaultValue": null,
      "extraTypeInfo": null,
      "filterable": true,
      "groupable": false,
      "inlineHelpText": null,
      "label": "Data da modificação do conteúdo",
      "name": "ContentModifiedDate",
      "nillable": true,
      "picklistValues": [],
      "referenceTo": [],
      "relationshipName": null,
      "sortable": true,
      "type": "datetime"
    },
    {
      "aggregatable": true,
      "custom": false,
      "defaultValue": null,
      "extraTypeInfo": null,
      "filterable": true,
      "groupable": true,
      "inlineHelpText": null,
      "label": "ID do arquivo de ativo",
      "name": "ContentAssetId",
      "nillable": true,
      "picklistValues": [],
      "referenceTo": [
        "ContentAsset"
      ],
      "relationshipName": "ContentAsset",
      "sortable": true,
      "type": "reference"
    }
  ],
  "label": "Documento de conteúdo",
  "childRelationships": [
    {
      "cascadeDelete": true,
      "childSObject": "AttachedContentDocument",
      "deprecatedAndHidden": false,
      "field": "ContentDocumentId",
      "junctionIdListNames": [],
      "junctionReferenceTo": [],
      "relationshipName": null,
      "restrictedDelete": false
    },
    {
      "cascadeDelete": false,
      "childSObject": "AuthorizationFormText",
      "deprecatedAndHidden": false,
      "field": "ContentDocumentId",
      "junctionIdListNames": [],
      "junctionReferenceTo": [],
      "relationshipName": "AuthorizationFormTexts",
      "restrictedDelete": true
    },
    {
      "cascadeDelete": false,
      "childSObject": "ContentAsset",
      "deprecatedAndHidden": false,
      "field": "ContentDocumentId",
      "junctionIdListNames": [],
      "junctionReferenceTo": [],
      "relationshipName": null,
      "restrictedDelete": false
    },
    {
      "cascadeDelete": false,
      "childSObject": "ContentDistribution",
      "deprecatedAndHidden": false,
      "field": "ContentDocumentId",
      "junctionIdListNames": [],
      "junctionReferenceTo": [],
      "relationshipName": "ContentDistributions",
      "restrictedDelete": false
    },
    {
      "cascadeDelete": true,
      "childSObject": "ContentDocumentFeed",
      "deprecatedAndHidden": false,
      "field": "ParentId",
      "junctionIdListNames": [],
      "junctionReferenceTo": [],
      "relationshipName": "Feeds",
      "restrictedDelete": false
    },
    {
      "cascadeDelete": true,
      "childSObject": "ContentDocumentHistory",
      "deprecatedAndHidden": false,
      "field": "ContentDocumentId",
      "junctionIdListNames": [],
      "junctionReferenceTo": [],
      "relationshipName": "Histories",
      "restrictedDelete": false
    },
    {
      "cascadeDelete": true,
      "childSObject": "ContentDocumentLink",
      "deprecatedAndHidden": false,
      "field": "ContentDocumentId",
      "junctionIdListNames": [],
      "junctionReferenceTo": [],
      "relationshipName": "ContentDocumentLinks",
      "restrictedDelete": false
    },
    {
      "cascadeDelete": false,
      "childSObject": "ContentDocumentLinkChangeEvent",
      "deprecatedAndHidden": false,
      "field": "ContentDocumentId",
      "junctionIdListNames": [],
      "junctionReferenceTo": [],
      "relationshipName": null,
      "restrictedDelete": false
    },
    {
      "cascadeDelete": true,
      "childSObject": "ContentDocumentSubscription",
      "deprecatedAndHidden": false,
      "field": "ContentDocumentId",
      "junctionIdListNames": [],
      "junctionReferenceTo": [],
      "relationshipName": null,
      "restrictedDelete": false
    },
    {
      "cascadeDelete": true,
      "childSObject": "ContentFolderMember",
      "deprecatedAndHidden": false,
      "field": "ChildRecordId",
      "junctionIdListNames": [],
      "junctionReferenceTo": [],
      "relationshipName": null,
      "restrictedDelete": false
    },
    {
      "cascadeDelete": false,
      "childSObject": "ContentNotification",
      "deprecatedAndHidden": false,
      "field": "EntityIdentifierId",
      "junctionIdListNames": [],
      "junctionReferenceTo": [],
      "relationshipName": null,
      "restrictedDelete": false
    },
    {
      "cascadeDelete": true,
      "childSObject": "ContentVersion",
      "deprecatedAndHidden": false,
      "field": "ContentDocumentId",
      "junctionIdListNames": [],
      "junctionReferenceTo": [],
      "relationshipName": "ContentVersions",
      "restrictedDelete": false
    },
    {
      "cascadeDelete": false,
      "childSObject": "ContentVersionChangeEvent",
      "deprecatedAndHidden": false,
      "field": "ContentDocumentId",
      "junctionIdListNames": [],
      "junctionReferenceTo": [],
      "relationshipName": null,
      "restrictedDelete": false
    },
    {
      "cascadeDelete": true,
      "childSObject": "ContentVersionComment",
      "deprecatedAndHidden": false,
      "field": "ContentDocumentId",
      "junctionIdListNames": [],
      "junctionReferenceTo": [],
      "relationshipName": null,
      "restrictedDelete": false
    },
    {
      "cascadeDelete": true,
      "childSObject": "ContentWorkspaceDoc",
      "deprecatedAndHidden": false,
      "field": "ContentDocumentId",
      "junctionIdListNames": [],
      "junctionReferenceTo": [],
      "relationshipName": null,
      "restrictedDelete": false
    },
    {
      "cascadeDelete": true,
      "childSObject": "EntitySubscription",
      "deprecatedAndHidden": false,
      "field": "ParentId",
      "junctionIdListNames": [],
      "junctionReferenceTo": [],
      "relationshipName": "FeedSubscriptionsForEntity",
      "restrictedDelete": false
    },
    {
      "cascadeDelete": false,
      "childSObject": "FeedAttachment",
      "deprecatedAndHidden": false,
      "field": "RecordId",
      "junctionIdListNames": [],
      "junctionReferenceTo": [],
      "relationshipName": null,
      "restrictedDelete": false
    },
    {
      "cascadeDelete": false,
      "childSObject": "FeedComment",
      "deprecatedAndHidden": false,
      "field": "ParentId",
      "junctionIdListNames": [],
      "junctionReferenceTo": [],
      "relationshipName": null,
      "restrictedDelete": false
    },
    {
      "cascadeDelete": true,
      "childSObject": "FeedItem",
      "deprecatedAndHidden": false,
      "field": "ParentId",
      "junctionIdListNames": [],
      "junctionReferenceTo": [],
      "relationshipName": null,
      "restrictedDelete": false
    },
    {
      "cascadeDelete": false,
      "childSObject": "FileEventStore",
      "deprecatedAndHidden": false,
      "field": "DocumentId",
      "junctionIdListNames": [],
      "junctionReferenceTo": [],
      "relationshipName": null,
      "restrictedDelete": false
    },
    {
      "cascadeDelete": false,
      "childSObject": "FlowExecutionErrorEvent",
      "deprecatedAndHidden": false,
      "field": "ContextRecordId",
      "junctionIdListNames": [],
      "junctionReferenceTo": [],
      "relationshipName": null,
      "restrictedDelete": false
    },
    {
      "cascadeDelete": false,
      "childSObject": "FlowRecordRelation",
      "deprecatedAndHidden": false,
      "field": "RelatedRecordId",
      "junctionIdListNames": [],
      "junctionReferenceTo": [],
      "relationshipName": null,
      "restrictedDelete": false
    },
    {
      "cascadeDelete": false,
      "childSObject": "FolderedContentDocument",
      "deprecatedAndHidden": false,
      "field": "ContentDocumentId",
      "junctionIdListNames": [],
      "junctionReferenceTo": [],
      "relationshipName": null,
      "restrictedDelete": false
    },
    {
      "cascadeDelete": true,
      "childSObject": "Image",
      "deprecatedAndHidden": false,
      "field": "ContentDocumentId",
      "junctionIdListNames": [],
      "junctionReferenceTo": [],
      "relationshipName": null,
      "restrictedDelete": false
    },
    {
      "cascadeDelete": true,
      "childSObject": "OwnedContentDocument",
      "deprecatedAndHidden": false,
      "field": "ContentDocumentId",
      "junctionIdListNames": [],
      "junctionReferenceTo": [],
      "relationshipName": null,
      "restrictedDelete": false
    },
    {
      "cascadeDelete": true,
      "childSObject": "TopicAssignment",
      "deprecatedAndHidden": false,
      "field": "EntityId",
      "junctionIdListNames": [],
      "junctionReferenceTo": [],
      "relationshipName": "TopicAssignments",
      "restrictedDelete": false
    },
    {
      "cascadeDelete": true,
      "childSObject": "VoiceCallRecording",
      "deprecatedAndHidden": false,
      "field": "MediaContentId",
      "junctionIdListNames": [],
      "junctionReferenceTo": [],
      "relationshipName": null,
      "restrictedDelete": false
    },
    {
      "cascadeDelete": false,
      "childSObject": "VoiceCallRecordingChangeEvent",
      "deprecatedAndHidden": false,
      "field": "MediaContentId",
      "junctionIdListNames": [],
      "junctionReferenceTo": [],
      "relationshipName": null,
      "restrictedDelete": false
    }
  ],
  "custom": false,
  "name": "ContentDocument",
  "queryable": true
}