{
  "fields": [
    {
      "aggregatable": true,
      "custom": false,
      "defaultValue": null,
      "extraTypeInfo": null,
      "filterable": true,
      "groupable": true,
      "inlineHelpText": null,
      "label": "ID do histórico do tipo de trabalho do canal de engajamento",
      "name": "Id",
      "nillable": false,
      "picklistValues": [],
      "referenceTo": [],
      "relationshipName": null,
      "sortable": true,
      "type": "id"
    },
    {
      "aggregatable": false,
      "custom": false,
      "defaultValue": false,
      "extraTypeInfo": null,
      "filterable": true,
      "groupable": true,
      "inlineHelpText": null,
      "label": "Excluído",
      "name": "IsDeleted",
      "nillable": false,
      "picklistValues": [],
      "referenceTo": [],
      "relationshipName": null,
      "sortable": true,
      "type": "boolean"
    },
    {
      "aggregatable": true,
      "custom": false,
      "defaultValue": null,
      "extraTypeInfo": null,
      "filterable": true,
      "groupable": true,
      "inlineHelpText": null,
      "label": "ID do tipo de trabalho do canal de engajamento",
      "name": "EngagementChannelWorkTypeId",
      "nillable": false,
      "picklistValues": [],
      "referenceTo": [
        "EngagementChannelWorkType"
      ],
      "relationshipName": "EngagementChannelWorkType",
      "sortable": true,
      "type": "reference"
    },
    {
      "aggregatable": true,
      "custom": false,
      "defaultValue": null,
      "extraTypeInfo": null,
      "filterable": true,
      "groupable": true,
      "inlineHelpText": null,
      "label": "Criado pelo ID",
      "name": "CreatedById",
      "nillable": false,
      "picklistValues": [],
      "referenceTo": [
        "User"
      ],
      "relationshipName": "CreatedBy",
      "sortable": true,
      "type": "reference"
    },
    {
      "aggregatable": true,
      "custom": false,
      "defaultValue": null,
      "extraTypeInfo": null,
      "filterable": true,
      "groupable": false,
      "inlineHelpText": null,
      "label": "Data de criação",
      "name": "CreatedDate",
      "nillable": false,
      "picklistValues": [],
      "referenceTo": [],
      "relationshipName": null,
      "sortable": true,
      "type": "datetime"
    },
    {
      "aggregatable": true,
      "custom": false,
      "defaultValue": null,
      "extraTypeInfo": null,
      "filterable": true,
      "groupable": true,
      "inlineHelpText": null,
      "label": "Campo alterado",
      "name": "Field",
      "nillable": false,
      "picklistValues": [
        {
          "active": true,
          "defaultValue": false,
          "label": "Código ISO da moeda",
          "validFor": null,
          "value": "CurrencyIsoCode"
        },
        {
          "active": true,
          "defaultValue": false,
          "label": "Criado",
          "validFor": null,
          "value": "created"
        },
        {
          "active": true,
          "defaultValue": false,
          "label": "Evento do feed",
          "validFor": null,
          "value": "feedEvent"
        },
        {
          "active": true,
          "defaultValue": false,
          "label": "Indivíduo mesclado",
          "validFor": null,
          "value": "individualMerged"
        },
        {
          "active": true,
          "defaultValue": false,
          "label": "Proprietário (Aceito)",
          "validFor": null,
          "value": "ownerAccepted"
        },
        {
          "active": true,
          "defaultValue": false,
          "label": "Proprietário (Atribuição)",
          "validFor": null,
          "value": "ownerAssignment"
        },
        {
          "active": true,
          "defaultValue": false,
          "label": "Registro bloqueado.",
          "validFor": null,
          "value": "locked"
        },
        {
          "active": true,
          "defaultValue": false,
          "label": "Registro desbloqueado.",
          "validFor": null,
          "value": "unlocked"
        },
        {
          "active": true,
          "defaultValue": false,
          "label": "Tipo de canal de engajamento",
          "validFor": null,
          "value": "EngagementChannelType"
        },
        {
          "active": true,
          "defaultValue": false,
          "label": "Tipo de trabalho",
          "validFor": null,
          "value": "WorkType"
        },
        {
          "active": true,
          "defaultValue": false,
          "label": "Todos os canais de engajamento suportados",
          "validFor": null,
          "value": "AreAllEngmtChnlSupported"
        }
      ],
      "referenceTo": [],
      "relationshipName": null,
      "sortable": true,
      "type": "picklist"
    },
    {
      "aggregatable": true,
      "custom": false,
      "defaultValue": null,
      "extraTypeInfo": null,
      "filterable": true,
      "groupable": true,
      "inlineHelpText": null,
      "label": "Tipo de dados",
      "name": "DataType",
      "nillable": true,
      "picklistValues": [
        {
          "active": true,
          "defaultValue": false,
          "label": null,
          "validFor": null,
          "value": "Address"
        },
        {
          "active": true,
          "defaultValue": false,
          "label": null,
          "validFor": null,
          "value": "AnyType"
        },
        {
          "active": true,
          "defaultValue": false,
          "label": null,
          "validFor": null,
          "value": "AutoNumber"
        },
        {
          "active": true,
          "defaultValue": false,
          "label": null,
          "validFor": null,
          "value": "Base64"
        },
        {
          "active": true,
          "defaultValue": false,
          "label": null,
          "validFor": null,
          "value": "BitVector"
        },
        {
          "active": true,
          "defaultValue": false,
          "label": null,
          "validFor": null,
          "value": "Boolean"
        },
        {
          "active": true,
          "defaultValue": false,
          "label": null,
          "validFor": null,
          "value": "Content"
        },
        {
          "active": true,
          "defaultValue": false,
          "label": null,
          "validFor": null,
          "value": "Currency"
        },
        {
          "active": true,
          "defaultValue": false,
          "label": null,
          "validFor": null,
          "value": "DataCategoryGroupReference"
        },
        {
          "active": true,
          "defaultValue": false,
          "label": null,
          "validFor": null,
          "value": "DateOnly"
        },
        {
          "active": true,
          "defaultValue": false,
          "label": null,
          "validFor": null,
          "value": "DateTime"
        },
        {
          "active": true,
          "defaultValue": false,
          "label": null,
          "validFor": null,
          "value": "Division"
        },
        {
          "active": true,
          "defaultValue": false,
          "label": null,
          "validFor": null,
          "value": "Double"
        },
        {
          "active": true,
          "defaultValue": false,
          "label": null,
          "validFor": null,
          "value": "DynamicEnum"
        },
        {
          "active": true,
          "defaultValue": false,
          "label": null,
          "validFor": null,
          "value": "Email"
        },
        {
          "active": true,
          "defaultValue": false,
          "label": null,
          "validFor": null,
          "value": "EncryptedBase64"
        },
        {
          "active": true,
          "defaultValue": false,
          "label": null,
          "validFor": null,
          "value": "EncryptedText"
        },
        {
          "active": true,
          "defaultValue": false,
          "label": null,
          "validFor": null,
          "value": "EntityId"
        },
        {
          "active": true,
          "defaultValue": false,
          "label": null,
          "validFor": null,
          "value": "EnumOrId"
        },
        {
          "active": true,
          "defaultValue": false,
          "label": null,
          "validFor": null,
          "value": "ExternalId"
        },
        {
          "active": true,
          "defaultValue": false,
          "label": null,
          "validFor": null,
          "value": "Fax"
        },
        {
          "active": true,
          "defaultValue": false,
          "label": null,
          "validFor": null,
          "value": "File"
        },
        {
          "active": true,
          "defaultValue": false,
          "label": null,
          "validFor": null,
          "value": "HtmlMultiLineText"
        },
        {
          "active": true,
          "defaultValue": false,
          "label": null,
          "validFor": null,
          "value": "HtmlStringPlusClob"
        },
        {
          "active": true,
          "defaultValue": false,
          "label": null,
          "validFor": null,
          "value": "InetAddress"
        },
        {
          "active": true,
          "defaultValue": false,
          "label": null,
          "validFor": null,
          "value": "Json"
        },
        {
          "active": true,
          "defaultValue": false,
          "label": null,
          "validFor": null,
          "value": "Location"
        },
        {
          "active": true,
          "defaultValue": false,
          "label": null,
          "validFor": null,
          "value": "MultiEnum"
        },
        {
          "active": true,
          "defaultValue": false,
          "label": null,
          "validFor": null,
          "value": "MultiLineText"
        },
        {
          "active": true,
          "defaultValue": false,
          "label": null,
          "validFor": null,
          "value": "Namespace"
        },
        {
          "active": true,
          "defaultValue": false,
          "label": null,
          "validFor": null,
          "value": "Percent"
        },
        {
          "active": true,
          "defaultValue": false,
          "label": null,
          "validFor": null,
          "value": "PersonName"
        },
        {
          "active": true,
          "defaultValue": false,
          "label": null,
          "validFor": null,
          "value": "Phone"
        },
        {
          "active": true,
          "defaultValue": false,
          "label": null,
          "validFor": null,
          "value": "Raw"
        },
        {
          "active": true,
          "defaultValue": false,
          "label": null,
          "validFor": null,
          "value": "RecordType"
        },
        {
          "active": true,
          "defaultValue": false,
          "label": null,
          "validFor": null,
          "value": "SfdcEncryptedText"
        },
        {
          "active": true,
          "defaultValue": false,
          "label": null,
          "validFor": null,
          "value": "SimpleNamespace"
        },
        {
          "active": true,
          "defaultValue": false,
          "label": null,
          "validFor": null,
          "value": "StringPlusClob"
        },
        {
          "active": true,
          "defaultValue": false,
          "label": null,
          "validFor": null,
          "value": "Switchable_PersonName"
        },
        {
          "active": true,
          "defaultValue": false,
          "label": null,
          "validFor": null,
          "value": "Text"
        },
        {
          "active": true,
          "defaultValue": false,
          "label": null,
          "validFor": null,
          "value": "TimeOnly"
        },
        {
          "active": true,
          "defaultValue": false,
          "label": null,
          "validFor": null,
          "value": "Url"
        },
        {
          "active": true,
          "defaultValue": false,
          "label": null,
          "validFor": null,
          "value": "YearQuarter"
        }
      ],
      "referenceTo": [],
      "relationshipName": null,
      "sortable": true,
      "type": "picklist"
    },
    {
      "aggregatable": false,
      "custom": false,
      "defaultValue": null,
      "extraTypeInfo": null,
      "filterable": false,
      "groupable": false,
      "inlineHelpText": null,
      "label": "Valor antigo",
      "name": "OldValue",
      "nillable": true,
      "picklistValues": [],
      "referenceTo": [],
      "relationshipName": null,
      "sortable": true,
      "type": "anyType"
    },
    {
      "aggregatable": false,
      "custom": false,
      "defaultValue": null,
      "extraTypeInfo": null,
      "filterable": false,
      "groupable": false,
      "inlineHelpText": null,
      "label": "Novo valor",
      "name": "NewValue",
      "nillable": true,
      "picklistValues": [],
      "referenceTo": [],
      "relationshipName": null,
      "sortable": true,
      "type": "anyType"
    }
  ],
  "label": "Histórico do tipo de trabalho do canal de engajamento",
  "childRelationships": [],
  "custom": false,
  "name": "EngagementChannelWorkTypeHistory",
  "queryable": true
}