{
  "fields": [
    {
      "aggregatable": true,
      "custom": false,
      "defaultValue": null,
      "extraTypeInfo": null,
      "filterable": true,
      "groupable": true,
      "inlineHelpText": null,
      "label": "ID da Credencial Nomeada",
      "name": "Id",
      "nillable": false,
      "picklistValues": [],
      "referenceTo": [],
      "relationshipName": null,
      "sortable": true,
      "type": "id"
    },
    {
      "aggregatable": false,
      "custom": false,
      "defaultValue": false,
      "extraTypeInfo": null,
      "filterable": true,
      "groupable": true,
      "inlineHelpText": null,
      "label": "Excluído",
      "name": "IsDeleted",
      "nillable": false,
      "picklistValues": [],
      "referenceTo": [],
      "relationshipName": null,
      "sortable": true,
      "type": "boolean"
    },
    {
      "aggregatable": true,
      "custom": false,
      "defaultValue": null,
      "extraTypeInfo": null,
      "filterable": true,
      "groupable": true,
      "inlineHelpText": null,
      "label": "Nome",
      "name": "DeveloperName",
      "nillable": false,
      "picklistValues": [],
      "referenceTo": [],
      "relationshipName": null,
      "sortable": true,
      "type": "string"
    },
    {
      "aggregatable": true,
      "custom": false,
      "defaultValue": null,
      "extraTypeInfo": null,
      "filterable": true,
      "groupable": true,
      "inlineHelpText": null,
      "label": "Idioma mestre",
      "name": "Language",
      "nillable": false,
      "picklistValues": [
        {
          "active": true,
          "defaultValue": false,
          "label": "Inglês",
          "validFor": null,
          "value": "en_US"
        },
        {
          "active": true,
          "defaultValue": false,
          "label": "Alemão",
          "validFor": null,
          "value": "de"
        },
        {
          "active": true,
          "defaultValue": false,
          "label": "Espanhol",
          "validFor": null,
          "value": "es"
        },
        {
          "active": true,
          "defaultValue": false,
          "label": "Francês",
          "validFor": null,
          "value": "fr"
        },
        {
          "active": true,
          "defaultValue": false,
          "label": "Italiano",
          "validFor": null,
          "value": "it"
        },
        {
          "active": true,
          "defaultValue": false,
          "label": "Japonês",
          "validFor": null,
          "value": "ja"
        },
        {
          "active": true,
          "defaultValue": false,
          "label": "Sueco",
          "validFor": null,
          "value": "sv"
        },
        {
          "active": true,
          "defaultValue": false,
          "label": "Coreano",
          "validFor": null,
          "value": "ko"
        },
        {
          "active": true,
          "defaultValue": false,
          "label": "Chinês (tradicional)",
          "validFor": null,
          "value": "zh_TW"
        },
        {
          "active": true,
          "defaultValue": false,
          "label": "Chinês (simplificado)",
          "validFor": null,
          "value": "zh_CN"
        },
        {
          "active": true,
          "defaultValue": false,
          "label": "Português (Brasil)",
          "validFor": null,
          "value": "pt_BR"
        },
        {
          "active": true,
          "defaultValue": false,
          "label": "Holandês",
          "validFor": null,
          "value": "nl_NL"
        },
        {
          "active": true,
          "defaultValue": false,
          "label": "Dinamarquês",
          "validFor": null,
          "value": "da"
        },
        {
          "active": true,
          "defaultValue": false,
          "label": "Tailandês",
          "validFor": null,
          "value": "th"
        },
        {
          "active": true,
          "defaultValue": false,
          "label": "Finlandês",
          "validFor": null,
          "value": "fi"
        },
        {
          "active": true,
          "defaultValue": false,
          "label": "Russo",
          "validFor": null,
          "value": "ru"
        },
        {
          "active": true,
          "defaultValue": false,
          "label": "Espanhol (México)",
          "validFor": null,
          "value": "es_MX"
        },
        {
          "active": true,
          "defaultValue": false,
          "label": "Norueguês",
          "validFor": null,
          "value": "no"
        }
      ],
      "referenceTo": [],
      "relationshipName": null,
      "sortable": true,
      "type": "picklist"
    },
    {
      "aggregatable": true,
      "custom": false,
      "defaultValue": null,
      "extraTypeInfo": null,
      "filterable": true,
      "groupable": true,
      "inlineHelpText": null,
      "label": "Rótulo",
      "name": "MasterLabel",
      "nillable": false,
      "picklistValues": [],
      "referenceTo": [],
      "relationshipName": null,
      "sortable": true,
      "type": "string"
    },
    {
      "aggregatable": true,
      "custom": false,
      "defaultValue": null,
      "extraTypeInfo": null,
      "filterable": true,
      "groupable": true,
      "inlineHelpText": null,
      "label": "Prefixo do namespace",
      "name": "NamespacePrefix",
      "nillable": true,
      "picklistValues": [],
      "referenceTo": [],
      "relationshipName": null,
      "sortable": true,
      "type": "string"
    },
    {
      "aggregatable": true,
      "custom": false,
      "defaultValue": null,
      "extraTypeInfo": null,
      "filterable": true,
      "groupable": false,
      "inlineHelpText": null,
      "label": "Data de criação",
      "name": "CreatedDate",
      "nillable": false,
      "picklistValues": [],
      "referenceTo": [],
      "relationshipName": null,
      "sortable": true,
      "type": "datetime"
    },
    {
      "aggregatable": true,
      "custom": false,
      "defaultValue": null,
      "extraTypeInfo": null,
      "filterable": true,
      "groupable": true,
      "inlineHelpText": null,
      "label": "Criado pelo ID",
      "name": "CreatedById",
      "nillable": false,
      "picklistValues": [],
      "referenceTo": [
        "User"
      ],
      "relationshipName": "CreatedBy",
      "sortable": true,
      "type": "reference"
    },
    {
      "aggregatable": true,
      "custom": false,
      "defaultValue": null,
      "extraTypeInfo": null,
      "filterable": true,
      "groupable": false,
      "inlineHelpText": null,
      "label": "Data da última modificação",
      "name": "LastModifiedDate",
      "nillable": false,
      "picklistValues": [],
      "referenceTo": [],
      "relationshipName": null,
      "sortable": true,
      "type": "datetime"
    },
    {
      "aggregatable": true,
      "custom": false,
      "defaultValue": null,
      "extraTypeInfo": null,
      "filterable": true,
      "groupable": true,
      "inlineHelpText": null,
      "label": "Última modificação pelo ID",
      "name": "LastModifiedById",
      "nillable": false,
      "picklistValues": [],
      "referenceTo": [
        "User"
      ],
      "relationshipName": "LastModifiedBy",
      "sortable": true,
      "type": "reference"
    },
    {
      "aggregatable": true,
      "custom": false,
      "defaultValue": null,
      "extraTypeInfo": null,
      "filterable": true,
      "groupable": false,
      "inlineHelpText": null,
      "label": "Modstamp do sistema",
      "name": "SystemModstamp",
      "nillable": false,
      "picklistValues": [],
      "referenceTo": [],
      "relationshipName": null,
      "sortable": true,
      "type": "datetime"
    },
    {
      "aggregatable": false,
      "custom": false,
      "defaultValue": null,
      "extraTypeInfo": "plaintextarea",
      "filterable": false,
      "groupable": false,
      "inlineHelpText": "O URL para se conectar ao sistema externo.",
      "label": "URL",
      "name": "Endpoint",
      "nillable": true,
      "picklistValues": [],
      "referenceTo": [],
      "relationshipName": null,
      "sortable": false,
      "type": "textarea"
    },
    {
      "aggregatable": true,
      "custom": false,
      "defaultValue": null,
      "extraTypeInfo": null,
      "filterable": true,
      "groupable": true,
      "inlineHelpText": "Usado para controlar os usuários que estão acessando o servidor externo. Anônimo implica que uma identidade de usuário não é especificada para o acesso do servidor externo. Entidade nomeada usa uma identidade de usuário para todos os usuários a fim de acessar o servidor externo.",
      "label": "Tipo de identidade",
      "name": "PrincipalType",
      "nillable": true,
      "picklistValues": [
        {
          "active": true,
          "defaultValue": false,
          "label": "Anônimo",
          "validFor": null,
          "value": "Anonymous"
        },
        {
          "active": true,
          "defaultValue": false,
          "label": "Por usuário",
          "validFor": null,
          "value": "PerUser"
        },
        {
          "active": true,
          "defaultValue": false,
          "label": "Principal nomeado",
          "validFor": null,
          "value": "NamedUser"
        }
      ],
      "referenceTo": [],
      "relationshipName": null,
      "sortable": true,
      "type": "picklist"
    },
    {
      "aggregatable": false,
      "custom": false,
      "defaultValue": null,
      "extraTypeInfo": null,
      "filterable": true,
      "groupable": false,
      "inlineHelpText": null,
      "label": "GenerateAuthorizationHeader",
      "name": "CalloutOptionsGenerateAuthorizationHeader",
      "nillable": false,
      "picklistValues": [],
      "referenceTo": [],
      "relationshipName": null,
      "sortable": false,
      "type": "boolean"
    },
    {
      "aggregatable": false,
      "custom": false,
      "defaultValue": null,
      "extraTypeInfo": null,
      "filterable": true,
      "groupable": false,
      "inlineHelpText": null,
      "label": "AllowMergeFieldsInHeader",
      "name": "CalloutOptionsAllowMergeFieldsInHeader",
      "nillable": false,
      "picklistValues": [],
      "referenceTo": [],
      "relationshipName": null,
      "sortable": false,
      "type": "boolean"
    },
    {
      "aggregatable": false,
      "custom": false,
      "defaultValue": null,
      "extraTypeInfo": null,
      "filterable": true,
      "groupable": false,
      "inlineHelpText": null,
      "label": "AllowMergeFieldsInBody",
      "name": "CalloutOptionsAllowMergeFieldsInBody",
      "nillable": false,
      "picklistValues": [],
      "referenceTo": [],
      "relationshipName": null,
      "sortable": false,
      "type": "boolean"
    },
    {
      "aggregatable": true,
      "custom": false,
      "defaultValue": null,
      "extraTypeInfo": null,
      "filterable": true,
      "groupable": true,
      "inlineHelpText": "Este serviço da Salesforce ou de terceiros fornece o processo de login e aprova o acesso ao sistema externo.",
      "label": "ID do provedor de autorização",
      "name": "AuthProviderId",
      "nillable": true,
      "picklistValues": [],
      "referenceTo": [
        "AuthProvider"
      ],
      "relationshipName": "AuthProvider",
      "sortable": true,
      "type": "reference"
    },
    {
      "aggregatable": true,
      "custom": false,
      "defaultValue": null,
      "extraTypeInfo": null,
      "filterable": true,
      "groupable": true,
      "inlineHelpText": null,
      "label": "Emissor de JWT",
      "name": "JwtIssuer",
      "nillable": true,
      "picklistValues": [],
      "referenceTo": [],
      "relationshipName": null,
      "sortable": true,
      "type": "string"
    },
    {
      "aggregatable": true,
      "custom": false,
      "defaultValue": null,
      "extraTypeInfo": null,
      "filterable": true,
      "groupable": true,
      "inlineHelpText": null,
      "label": "Assunto de fórmula de JWT",
      "name": "JwtFormulaSubject",
      "nillable": true,
      "picklistValues": [],
      "referenceTo": [],
      "relationshipName": null,
      "sortable": true,
      "type": "string"
    },
    {
      "aggregatable": true,
      "custom": false,
      "defaultValue": null,
      "extraTypeInfo": null,
      "filterable": true,
      "groupable": true,
      "inlineHelpText": null,
      "label": "Assunto de texto de JWT",
      "name": "JwtTextSubject",
      "nillable": true,
      "picklistValues": [],
      "referenceTo": [],
      "relationshipName": null,
      "sortable": true,
      "type": "string"
    },
    {
      "aggregatable": true,
      "custom": false,
      "defaultValue": null,
      "extraTypeInfo": null,
      "filterable": true,
      "groupable": true,
      "inlineHelpText": null,
      "label": "Período de validade de JWT em segundos",
      "name": "JwtValidityPeriodSeconds",
      "nillable": true,
      "picklistValues": [],
      "referenceTo": [],
      "relationshipName": null,
      "sortable": true,
      "type": "int"
    },
    {
      "aggregatable": false,
      "custom": false,
      "defaultValue": null,
      "extraTypeInfo": "plaintextarea",
      "filterable": false,
      "groupable": false,
      "inlineHelpText": null,
      "label": "Públicos de JWT",
      "name": "JwtAudience",
      "nillable": true,
      "picklistValues": [],
      "referenceTo": [],
      "relationshipName": null,
      "sortable": false,
      "type": "textarea"
    },
    {
      "aggregatable": false,
      "custom": false,
      "defaultValue": null,
      "extraTypeInfo": "plaintextarea",
      "filterable": false,
      "groupable": false,
      "inlineHelpText": null,
      "label": "URL de ponto final de token de autenticação",
      "name": "AuthTokenEndpointUrl",
      "nillable": true,
      "picklistValues": [],
      "referenceTo": [],
      "relationshipName": null,
      "sortable": false,
      "type": "textarea"
    }
  ],
  "label": "Credencial Nomeada",
  "childRelationships": [
    {
      "cascadeDelete": true,
      "childSObject": "CustomHttpHeader",
      "deprecatedAndHidden": false,
      "field": "ParentId",
      "junctionIdListNames": [],
      "junctionReferenceTo": [],
      "relationshipName": "CustomHttpHeaders",
      "restrictedDelete": false
    },
    {
      "cascadeDelete": false,
      "childSObject": "ExternalDataSource",
      "deprecatedAndHidden": false,
      "field": "NamedCredentialId",
      "junctionIdListNames": [],
      "junctionReferenceTo": [],
      "relationshipName": null,
      "restrictedDelete": true
    },
    {
      "cascadeDelete": true,
      "childSObject": "ExternalDataUserAuth",
      "deprecatedAndHidden": false,
      "field": "ExternalDataSourceId",
      "junctionIdListNames": [],
      "junctionReferenceTo": [],
      "relationshipName": "UserAuths",
      "restrictedDelete": false
    },
    {
      "cascadeDelete": false,
      "childSObject": "PaymentGateway",
      "deprecatedAndHidden": false,
      "field": "MerchantCredentialId",
      "junctionIdListNames": [],
      "junctionReferenceTo": [],
      "relationshipName": "PaymentGateways",
      "restrictedDelete": true
    },
    {
      "cascadeDelete": true,
      "childSObject": "SetupEntityAccess",
      "deprecatedAndHidden": false,
      "field": "SetupEntityId",
      "junctionIdListNames": [],
      "junctionReferenceTo": [],
      "relationshipName": "SetupEntityAccessItems",
      "restrictedDelete": false
    },
    {
      "cascadeDelete": false,
      "childSObject": "UserProvisioningConfig",
      "deprecatedAndHidden": false,
      "field": "NamedCredentialId",
      "junctionIdListNames": [],
      "junctionReferenceTo": [],
      "relationshipName": null,
      "restrictedDelete": true
    }
  ],
  "custom": false,
  "name": "NamedCredential",
  "queryable": true
}