{
  "fields": [
    {
      "aggregatable": true,
      "custom": false,
      "defaultValue": null,
      "extraTypeInfo": null,
      "filterable": true,
      "groupable": true,
      "inlineHelpText": null,
      "label": "ID do período",
      "name": "Id",
      "nillable": false,
      "picklistValues": [],
      "referenceTo": [],
      "relationshipName": null,
      "sortable": true,
      "type": "id"
    },
    {
      "aggregatable": true,
      "custom": false,
      "defaultValue": null,
      "extraTypeInfo": null,
      "filterable": true,
      "groupable": true,
      "inlineHelpText": null,
      "label": "ID das configurações do ano fiscal",
      "name": "FiscalYearSettingsId",
      "nillable": true,
      "picklistValues": [],
      "referenceTo": [
        "FiscalYearSettings"
      ],
      "relationshipName": "FiscalYearSettings",
      "sortable": true,
      "type": "reference"
    },
    {
      "aggregatable": true,
      "custom": false,
      "defaultValue": null,
      "extraTypeInfo": null,
      "filterable": true,
      "groupable": true,
      "inlineHelpText": null,
      "label": "Tipo",
      "name": "Type",
      "nillable": true,
      "picklistValues": [
        {
          "active": true,
          "defaultValue": false,
          "label": null,
          "validFor": null,
          "value": "Month"
        },
        {
          "active": true,
          "defaultValue": false,
          "label": null,
          "validFor": null,
          "value": "Quarter"
        },
        {
          "active": true,
          "defaultValue": false,
          "label": null,
          "validFor": null,
          "value": "Week"
        },
        {
          "active": true,
          "defaultValue": false,
          "label": null,
          "validFor": null,
          "value": "Year"
        }
      ],
      "referenceTo": [],
      "relationshipName": null,
      "sortable": true,
      "type": "picklist"
    },
    {
      "aggregatable": true,
      "custom": false,
      "defaultValue": null,
      "extraTypeInfo": null,
      "filterable": true,
      "groupable": true,
      "inlineHelpText": null,
      "label": "Data de início",
      "name": "StartDate",
      "nillable": false,
      "picklistValues": [],
      "referenceTo": [],
      "relationshipName": null,
      "sortable": true,
      "type": "date"
    },
    {
      "aggregatable": true,
      "custom": false,
      "defaultValue": null,
      "extraTypeInfo": null,
      "filterable": true,
      "groupable": true,
      "inlineHelpText": null,
      "label": "Data de término",
      "name": "EndDate",
      "nillable": false,
      "picklistValues": [],
      "referenceTo": [],
      "relationshipName": null,
      "sortable": true,
      "type": "date"
    },
    {
      "aggregatable": true,
      "custom": false,
      "defaultValue": null,
      "extraTypeInfo": null,
      "filterable": true,
      "groupable": false,
      "inlineHelpText": null,
      "label": "Modstamp do sistema",
      "name": "SystemModstamp",
      "nillable": false,
      "picklistValues": [],
      "referenceTo": [],
      "relationshipName": null,
      "sortable": true,
      "type": "datetime"
    },
    {
      "aggregatable": false,
      "custom": false,
      "defaultValue": false,
      "extraTypeInfo": null,
      "filterable": true,
      "groupable": true,
      "inlineHelpText": null,
      "label": "Período de previsão",
      "name": "IsForecastPeriod",
      "nillable": false,
      "picklistValues": [],
      "referenceTo": [],
      "relationshipName": null,
      "sortable": true,
      "type": "boolean"
    },
    {
      "aggregatable": true,
      "custom": false,
      "defaultValue": "Spring",
      "extraTypeInfo": null,
      "filterable": true,
      "groupable": true,
      "inlineHelpText": null,
      "label": "Nome do trimestre",
      "name": "QuarterLabel",
      "nillable": true,
      "picklistValues": [
        {
          "active": true,
          "defaultValue": true,
          "label": "Spring",
          "validFor": null,
          "value": "Spring"
        },
        {
          "active": true,
          "defaultValue": false,
          "label": "Summer",
          "validFor": null,
          "value": "Summer"
        },
        {
          "active": true,
          "defaultValue": false,
          "label": "Fall",
          "validFor": null,
          "value": "Fall"
        },
        {
          "active": true,
          "defaultValue": false,
          "label": "Winter",
          "validFor": null,
          "value": "Winter"
        }
      ],
      "referenceTo": [],
      "relationshipName": null,
      "sortable": true,
      "type": "picklist"
    },
    {
      "aggregatable": true,
      "custom": false,
      "defaultValue": null,
      "extraTypeInfo": null,
      "filterable": true,
      "groupable": true,
      "inlineHelpText": null,
      "label": "Nome do período",
      "name": "PeriodLabel",
      "nillable": true,
      "picklistValues": [],
      "referenceTo": [],
      "relationshipName": null,
      "sortable": true,
      "type": "picklist"
    },
    {
      "aggregatable": true,
      "custom": false,
      "defaultValue": null,
      "extraTypeInfo": null,
      "filterable": true,
      "groupable": true,
      "inlineHelpText": null,
      "label": "Número",
      "name": "Number",
      "nillable": true,
      "picklistValues": [],
      "referenceTo": [],
      "relationshipName": null,
      "sortable": true,
      "type": "int"
    },
    {
      "aggregatable": true,
      "custom": false,
      "defaultValue": null,
      "extraTypeInfo": null,
      "filterable": false,
      "groupable": true,
      "inlineHelpText": null,
      "label": "Rótulo totalmente qualificado",
      "name": "FullyQualifiedLabel",
      "nillable": true,
      "picklistValues": [],
      "referenceTo": [],
      "relationshipName": null,
      "sortable": false,
      "type": "string"
    }
  ],
  "label": "Período",
  "childRelationships": [
    {
      "cascadeDelete": true,
      "childSObject": "FiscalYearSettings",
      "deprecatedAndHidden": false,
      "field": "PeriodId",
      "junctionIdListNames": [],
      "junctionReferenceTo": [],
      "relationshipName": null,
      "restrictedDelete": false
    }
  ],
  "custom": false,
  "name": "Period",
  "queryable": true
}