{
  "fields": [
    {
      "aggregatable": true,
      "custom": false,
      "defaultValue": null,
      "extraTypeInfo": null,
      "filterable": true,
      "groupable": true,
      "inlineHelpText": null,
      "label": "ID do Feedback de detecção de ameaças",
      "name": "Id",
      "nillable": false,
      "picklistValues": [],
      "referenceTo": [],
      "relationshipName": null,
      "sortable": true,
      "type": "id"
    },
    {
      "aggregatable": true,
      "custom": false,
      "defaultValue": null,
      "extraTypeInfo": null,
      "filterable": true,
      "groupable": false,
      "inlineHelpText": null,
      "label": "Nome do feedback de detecção de ameaças",
      "name": "ThreatDetectionFeedbackNumber",
      "nillable": false,
      "picklistValues": [],
      "referenceTo": [],
      "relationshipName": null,
      "sortable": true,
      "type": "string"
    },
    {
      "aggregatable": true,
      "custom": false,
      "defaultValue": null,
      "extraTypeInfo": null,
      "filterable": true,
      "groupable": false,
      "inlineHelpText": null,
      "label": "Data de criação",
      "name": "CreatedDate",
      "nillable": false,
      "picklistValues": [],
      "referenceTo": [],
      "relationshipName": null,
      "sortable": true,
      "type": "datetime"
    },
    {
      "aggregatable": true,
      "custom": false,
      "defaultValue": null,
      "extraTypeInfo": null,
      "filterable": true,
      "groupable": true,
      "inlineHelpText": null,
      "label": "Criado pelo ID",
      "name": "CreatedById",
      "nillable": false,
      "picklistValues": [],
      "referenceTo": [
        "User"
      ],
      "relationshipName": "CreatedBy",
      "sortable": true,
      "type": "reference"
    },
    {
      "aggregatable": true,
      "custom": false,
      "defaultValue": null,
      "extraTypeInfo": null,
      "filterable": true,
      "groupable": false,
      "inlineHelpText": null,
      "label": "Data da última atualização",
      "name": "LastModifiedDate",
      "nillable": false,
      "picklistValues": [],
      "referenceTo": [],
      "relationshipName": null,
      "sortable": true,
      "type": "datetime"
    },
    {
      "aggregatable": true,
      "custom": false,
      "defaultValue": null,
      "extraTypeInfo": null,
      "filterable": true,
      "groupable": true,
      "inlineHelpText": null,
      "label": "Última modificação pelo ID",
      "name": "LastModifiedById",
      "nillable": false,
      "picklistValues": [],
      "referenceTo": [
        "User"
      ],
      "relationshipName": "LastModifiedBy",
      "sortable": true,
      "type": "reference"
    },
    {
      "aggregatable": true,
      "custom": false,
      "defaultValue": null,
      "extraTypeInfo": null,
      "filterable": true,
      "groupable": false,
      "inlineHelpText": null,
      "label": "Modstamp do sistema",
      "name": "SystemModstamp",
      "nillable": false,
      "picklistValues": [],
      "referenceTo": [],
      "relationshipName": null,
      "sortable": true,
      "type": "datetime"
    },
    {
      "aggregatable": true,
      "custom": false,
      "defaultValue": null,
      "extraTypeInfo": null,
      "filterable": true,
      "groupable": false,
      "inlineHelpText": null,
      "label": "Data da última visualização",
      "name": "LastViewedDate",
      "nillable": true,
      "picklistValues": [],
      "referenceTo": [],
      "relationshipName": null,
      "sortable": true,
      "type": "datetime"
    },
    {
      "aggregatable": true,
      "custom": false,
      "defaultValue": null,
      "extraTypeInfo": null,
      "filterable": true,
      "groupable": false,
      "inlineHelpText": null,
      "label": "Última data citada",
      "name": "LastReferencedDate",
      "nillable": true,
      "picklistValues": [],
      "referenceTo": [],
      "relationshipName": null,
      "sortable": true,
      "type": "datetime"
    },
    {
      "aggregatable": true,
      "custom": false,
      "defaultValue": null,
      "extraTypeInfo": null,
      "filterable": true,
      "groupable": true,
      "inlineHelpText": null,
      "label": "ID do usuário",
      "name": "UserId",
      "nillable": true,
      "picklistValues": [],
      "referenceTo": [
        "User"
      ],
      "relationshipName": "User",
      "sortable": true,
      "type": "reference"
    },
    {
      "aggregatable": true,
      "custom": false,
      "defaultValue": null,
      "extraTypeInfo": null,
      "filterable": true,
      "groupable": true,
      "inlineHelpText": null,
      "label": "Nome do usuário",
      "name": "Username",
      "nillable": true,
      "picklistValues": [],
      "referenceTo": [],
      "relationshipName": null,
      "sortable": true,
      "type": "string"
    },
    {
      "aggregatable": true,
      "custom": false,
      "defaultValue": null,
      "extraTypeInfo": null,
      "filterable": true,
      "groupable": true,
      "inlineHelpText": null,
      "label": "ID do evento de detecção de ameaças associado",
      "name": "ThreatDetectionEventId",
      "nillable": true,
      "picklistValues": [],
      "referenceTo": [
        "ApiAnomalyEventStore",
        "CredentialStuffingEventStore",
        "ReportAnomalyEventStore",
        "SessionHijackingEventStore"
      ],
      "relationshipName": "ThreatDetectionEvent",
      "sortable": true,
      "type": "reference"
    },
    {
      "aggregatable": true,
      "custom": false,
      "defaultValue": null,
      "extraTypeInfo": null,
      "filterable": true,
      "groupable": true,
      "inlineHelpText": null,
      "label": "Resposta",
      "name": "Response",
      "nillable": false,
      "picklistValues": [
        {
          "active": true,
          "defaultValue": false,
          "label": "Malicious",
          "validFor": null,
          "value": "Malicious"
        },
        {
          "active": true,
          "defaultValue": false,
          "label": "Suspicious",
          "validFor": null,
          "value": "Suspicious"
        },
        {
          "active": true,
          "defaultValue": false,
          "label": "Not a Threat",
          "validFor": null,
          "value": "Not a Threat"
        },
        {
          "active": true,
          "defaultValue": false,
          "label": "Unknown",
          "validFor": null,
          "value": "Unknown"
        }
      ],
      "referenceTo": [],
      "relationshipName": null,
      "sortable": true,
      "type": "picklist"
    }
  ],
  "label": "Feedback de detecção de ameaças",
  "childRelationships": [
    {
      "cascadeDelete": true,
      "childSObject": "AttachedContentDocument",
      "deprecatedAndHidden": false,
      "field": "LinkedEntityId",
      "junctionIdListNames": [],
      "junctionReferenceTo": [],
      "relationshipName": "AttachedContentDocuments",
      "restrictedDelete": false
    },
    {
      "cascadeDelete": true,
      "childSObject": "CombinedAttachment",
      "deprecatedAndHidden": false,
      "field": "ParentId",
      "junctionIdListNames": [],
      "junctionReferenceTo": [],
      "relationshipName": "CombinedAttachments",
      "restrictedDelete": false
    },
    {
      "cascadeDelete": true,
      "childSObject": "ContentDocumentLink",
      "deprecatedAndHidden": false,
      "field": "LinkedEntityId",
      "junctionIdListNames": [],
      "junctionReferenceTo": [],
      "relationshipName": "ContentDocumentLinks",
      "restrictedDelete": false
    },
    {
      "cascadeDelete": false,
      "childSObject": "ContentDocumentLinkChangeEvent",
      "deprecatedAndHidden": false,
      "field": "LinkedEntityId",
      "junctionIdListNames": [],
      "junctionReferenceTo": [],
      "relationshipName": null,
      "restrictedDelete": false
    },
    {
      "cascadeDelete": false,
      "childSObject": "ContentVersion",
      "deprecatedAndHidden": false,
      "field": "FirstPublishLocationId",
      "junctionIdListNames": [],
      "junctionReferenceTo": [],
      "relationshipName": null,
      "restrictedDelete": false
    },
    {
      "cascadeDelete": false,
      "childSObject": "ContentVersionChangeEvent",
      "deprecatedAndHidden": false,
      "field": "FirstPublishLocationId",
      "junctionIdListNames": [],
      "junctionReferenceTo": [],
      "relationshipName": null,
      "restrictedDelete": false
    },
    {
      "cascadeDelete": true,
      "childSObject": "EntitySubscription",
      "deprecatedAndHidden": false,
      "field": "ParentId",
      "junctionIdListNames": [],
      "junctionReferenceTo": [],
      "relationshipName": "FeedSubscriptionsForEntity",
      "restrictedDelete": false
    },
    {
      "cascadeDelete": false,
      "childSObject": "FeedComment",
      "deprecatedAndHidden": false,
      "field": "ParentId",
      "junctionIdListNames": [],
      "junctionReferenceTo": [],
      "relationshipName": null,
      "restrictedDelete": false
    },
    {
      "cascadeDelete": true,
      "childSObject": "FeedItem",
      "deprecatedAndHidden": false,
      "field": "ParentId",
      "junctionIdListNames": [],
      "junctionReferenceTo": [],
      "relationshipName": null,
      "restrictedDelete": false
    },
    {
      "cascadeDelete": false,
      "childSObject": "FlowExecutionErrorEvent",
      "deprecatedAndHidden": false,
      "field": "ContextRecordId",
      "junctionIdListNames": [],
      "junctionReferenceTo": [],
      "relationshipName": null,
      "restrictedDelete": false
    },
    {
      "cascadeDelete": false,
      "childSObject": "FlowRecordRelation",
      "deprecatedAndHidden": false,
      "field": "RelatedRecordId",
      "junctionIdListNames": [],
      "junctionReferenceTo": [],
      "relationshipName": null,
      "restrictedDelete": false
    },
    {
      "cascadeDelete": true,
      "childSObject": "ThreatDetectionFeedbackFeed",
      "deprecatedAndHidden": false,
      "field": "ParentId",
      "junctionIdListNames": [],
      "junctionReferenceTo": [],
      "relationshipName": "Feeds",
      "restrictedDelete": false
    }
  ],
  "custom": false,
  "name": "ThreatDetectionFeedback",
  "queryable": true
}